Clk_div.v
//  ----------------------------------------------------------------------
//
//  Module Name :		 Clk_div
//  Designer :			 Shimada
//  Create Date :		 2013/02/07
//  Update Date :		 2014/03/11
//  Version :				 1.0.2
//  HDL :            Verilog-HDL 2001
//  Target Device :	 DE0
//  Tool version :   Quartus II Web Edition (Version 13.1)
//  Description :		 エッジ・トリガ型 非同期リセット プリスケーラ(分周)回路
//									 デューティ比50%の矩形波を出力する
//
//  ----------------------------------------------------------------------



module Clk_div (
  input  clk,          // Clock (50MHz)
  input  rst,          // Asynchronous Reset active low
  input  [25:0] div,   // f(50M)/N  (N = div)
  output pclk          // Prescaler Clock
);

	reg  [25:0] cnt = 26'd0;


	always @(posedge clk or negedge rst) begin
	  if(~rst)
	  	cnt <= div;
	  else
			cnt <= (cnt < (div - 1'd1)) ? cnt + 1'd1 : 26'd0;
	end

	assign  pclk = (cnt < (div >> 1)) ? 1'b1 : 1'b0;


endmodule

SegDecCount/SegBlink.v
//  ----------------------------------------------------------------------
//
//  Module Name :    SegBlink
//  Designer :       Shimada
//  Create Date :    2014/02/26
//  Update Date :    2014/04/14
//  Version :        1.0.2
//  HDL :            Verilog-HDL 2001
//  Target Device :  DE0
//  Tool version :   Quartus II Web Edition (Version 13.1)
//  Description :    セグメントの点滅回路(1.25Hz)
//
//  ----------------------------------------------------------------------



module SegBlink (
  input clk,              // Clock (50MHz)
  input en,               // Enable
  input rst,              // Asynchronous Reset active low
  input  [7:0] seg_in,    // Input Segment Value
  output [7:0] seg_out    // output Segment Value
);

  wire  pclk;


  Clk_div blink_clk (clk, rst, 26'd40000000, pclk);      // 1.25Hzのクロックを生成

  assign  seg_out = (~en)  ? seg_in :                    // EnableがOFFの時は点滅しない
                    (pclk) ? seg_in : 8'b11111111;       // 入力値を点滅して返す


endmodule

SegDecCount/HexSegDec.v
//  ----------------------------------------------------------------------
//
//  Module Name :    HexSegDec
//  Designer :       Shimada
//  Create Date :    2013/02/07
//  Update Date :    2014/02/14
//  Version :        1.0.0
//  HDL :            Verilog-HDL 2001
//  Target Device :  DE0
//  Tool version :   Quartus II Web Edition (Version 13.1)
//  Description :    ７セグメントデコーダー
//
//  ----------------------------------------------------------------------



module HexSegDec (
  input  en,            // Enable
  input  rst,           // Asynchronous reset active low
  input  [3:0] value,   // Decimal Value (0~9), Dot(10), E(11), OFF(12~15)
  output [7:0] seg      // 7-Segment Display with decimal point
);


  function [7:0] LedDec (
    input  [3:0] num
  );

    begin
      case (num)
        4'd0:     LedDec = 8'b11000000;   // 0
        4'd1:     LedDec = 8'b11111001;   // 1
        4'd2:     LedDec = 8'b10100100;   // 2
        4'd3:     LedDec = 8'b10110000;   // 3
        4'd4:     LedDec = 8'b10011001;   // 4
        4'd5:     LedDec = 8'b10010010;   // 5
        4'd6:     LedDec = 8'b10000010;   // 6
        4'd7:     LedDec = 8'b11111000;   // 7
        4'd8:     LedDec = 8'b10000000;   // 8
        4'd9:     LedDec = 8'b10011000;   // 9
        4'd10:    LedDec = 8'b01111111;   // .
        4'd11:    LedDec = 8'b10000110;   // E
        default:  LedDec = 8'b11111111;   // LED OFF
      endcase
    end
  endfunction

  assign  seg = (~rst) ? 8'b00000000 :                  // Reset: All LED ON
                  (en) ? LedDec(value) : 8'b11111111;   // Enable OFF: All LED OFF


endmodule

SegDecCount/BcdCounter.v
//  ----------------------------------------------------------------------
//
//  Module Name :    BCD Counter
//  Designer :       Shimada
//  Create Date :    2014/01/22
//  Update Date :    2014/03/12
//  Version :        1.0.2
//  HDL :            Verilog-HDL 2001
//  Target Device :  DE0
//  Tool version :   Quartus II Web Edition (Version 13.1)
//  Description :    ボタンを押す毎にカウントアップ(10進数)して
//                   セグメントに表示する
//
//  ----------------------------------------------------------------------



module BcdCounter (
  input  clk,                    // Clock (50MHz)
  input  en,                     // Segment Enable
  input  we,                     // Write Count Enable
  input  rst,                    // Asynchronous Reset active low
  input  btn,                    // Pull Up Push Button
  output [7:0] seg,              // 7-Segment Display with decimal point
  output reg [3:0] cnt = 4'd0    // Count value (0~9)
);


  /*   Decimal Count Up (0~9)   */
  always @(negedge btn or negedge rst) begin
    if(~rst)
      cnt <= 4'd0;
    else if (we)
      cnt <= (cnt >= 4'd9) ? 4'd0 : cnt + 4'd1;
    else
      cnt <= cnt;
  end

  /*   Decimal to Hex Converter   */
  HexSegDec DisplaySeg (en, rst, cnt, seg);


endmodule

SegDecCount/BcdCountSegDisplay.v
module BcdCountSegDisplay (
  input  clk,           // Clock
  input  en,            // Enable
  input  rst,           // Asynchronous reset active low
  input  we,            // Digit Write Enable
  input  btn,           // Pull-up Push Button
  output [7:0] seg,     // 7-Segment Display with decimal point
  output [3:0] value    // 1-Digit Delay Value
);

  wire  [7:0] seg_in;


  /*   1-Digit Delay Value Counter   */
  BcdCounter DecCounter (clk, en, we, rst, btn, seg_in, value);
  /*   7-Segment Blinking   */
  SegBlink  SegBlinking (clk, we, rst, seg_in, seg);


endmodule

SegDecCount/Chattering.v
//  ----------------------------------------------------------------------
//
//  Module Name :    Chattering
//  Designer :       Shimada
//  Create Date :    2014/01/21
//  Update Date :    2014/02/14
//  Version :        0.9.9
//  HDL :            Verilog-HDL 2001
//  Target Device :  DE0
//  Tool version :   Quartus II Web Edition (Version 13.1)
//  Description :    チャタリング防止回路
//                   待機時間は7[ms]
//
//  ----------------------------------------------------------------------



module Chattering (
  input  clk,     // Clock (50MHz)
  input  rst,     // Asynchronous Reset active low
  input  btn,     // Pull-up Push Button
  output btn_cp   // Chattering-proof Output
  );

  wire clk_1khz;
  reg [7:0]  btn_buff = 8'b01111111;


  Clk_div gene_1khz (clk, rst, 16'd50000, clk_1khz);     // 1[KHz]のクロックを生成

  always @(posedge clk_1khz or negedge rst) begin
    if (~rst)
      btn_buff <= 8'b11111111;
    else
      btn_buff <= (btn_buff << 1) + btn;
  end


  assign  btn_cp = (btn_buff == 8'b10000000) ? 1'b0 : 	      	 // ON
	                 (btn_buff == 8'b01111111) ? 1'b1 : btn_cp;  	 // OFF


endmodule

DigitMove.v
//  ----------------------------------------------------------------------
//
//  Module Name :    Digit Move
//  Designer :       Shimada
//  Create Date :    2014/03/12
//  Update Date :    2014/04/13
//  Version :        1.0.1
//  HDL :            Verilog-HDL 2001
//  Target Device :  DE0
//  Tool version :   Quartus II Web Edition (Version 13.1)
//  Description :    桁移動ロジック回路
//
//  ----------------------------------------------------------------------



module DigitMove #(
  parameter  width = 4
)(
  input  btn,                           // Pull-up Push Button
  input  rst,                           // Asynchronous reset active low
  output [width-1:0] en,                // Enable
  output reg [width-1:0] selector = 0   // Selector
);


  always @(posedge btn or negedge rst) begin
    if (~rst)                    // Reset
      selector <= 0;
    else if (selector == 0)      // Bit Shift
      selector <= 1'b1;
    else
      selector <= selector << 1;
  end

  assign  en[width-1:0] = ~0;    // Enable Signal


endmodule

SegDecCount/SegDecCount.v
//  ----------------------------------------------------------------------
//
//  Module Name :    SegDecCount
//  Designer :       Shimada
//  Create Date :    2014/04/13
//  Update Date :    2014/04/13
//  Version :        1.0.0
//  HDL :            Verilog-HDL 2001
//  Target Device :  DE0
//  Tool version :   Quartus II Web Edition (Version 13.1)
//  Description :    10進数カウンタ回路 (0~9999)  widthで桁数を指定
//                   btn1で桁移動, btn2で指定した桁のカウントアップ
//
//  ----------------------------------------------------------------------



module SegDecCount #(
  parameter  width = 4        // Number of digits
)(
  input  clk,                 // Clock
  input  rst,                 // Asynchronous reset active low
  input  [1:0] btn,           // Pull-up Push Button
  output [7:0] seg0,          // 7-Segment Display with decimal point
  output [7:0] seg1,          // 7-Segment Display with decimal point
  output [7:0] seg2,          // 7-Segment Display with decimal point
  output [7:0] seg3,          // 7-Segment Display with decimal point
  output [13:0] count_value   // Count Value (0~9999)
);

  wire  [1:0] btn_cp;         // Chattering Prevention Button
  wire  [3:0] en;             // Segment Enable
  wire  [3:0] select_digit;   // Selected Digit
  wire  [3:0] digit_0;        // 1st Digit
  wire  [3:0] digit_1;        // 2nd Digit
  wire  [3:0] digit_2;        // 3rd Digit
  wire  [3:0] digit_3;        // 4th Digit


  /*   Digit Move   */
  Chattering btn0_chatter (clk, rst, btn[0], btn_cp[0]);          // Chattering Prevention
  DigitMove #(width) DigitShift (btn_cp[0], rst, en, select_digit);   // Digit Move by Button


  /*   Chattering Prevention   */
  Chattering btn1_chatter (clk, rst, btn[1], btn_cp[1]);


  /* Button Counter and 7-Segment Output */
  BcdCountSegDisplay digit0 (clk, en[0], rst, select_digit[0], btn_cp[1], seg0, digit_0);    // 1st Digit
  BcdCountSegDisplay digit1 (clk, en[1], rst, select_digit[1], btn_cp[1], seg1, digit_1);    // 2nd Digit
  BcdCountSegDisplay digit2 (clk, en[2], rst, select_digit[2], btn_cp[1], seg2, digit_2);    // 3rd Digit
  BcdCountSegDisplay digit3 (clk, en[3], rst, select_digit[3], btn_cp[1], seg3, digit_3);    // 4th Digit


  /*   Digit Adder   */
  assign  count_value = (14'd1000 * digit_3) + (14'd100 * digit_2) + (14'd10 * digit_1) + digit_0;


endmodule

SegDecCount/Simulator.v
//  ----------------------------------------------------------------------
//
//  Module Name :    Simulator
//  Designer :       Shimada
//  Create Date :    2014/02/11
//  Update Date :    2014/02/14
//  Version :        1.0.0
//  HDL :            Verilog-HDL 2001
//  Tool version :   Icarus Verilog  (Version 0.9.7)
//                   GTKWave  (Version 3.3.57)
//                   XQuartz  (Version 2.7.5)
//  Description :    シミュレーション用のテンプレート
//
//  ----------------------------------------------------------------------



`timescale 1ns/1ns

module Simulator;

  parameter  CYCLE      = 20;     // Clock Cycle
  parameter  HALF_CYCLE = 10;     // Clock half-Cycle
  parameter  DELAY      = 10;     // Racing measures

  reg  clk;
  reg  rst;
  reg  [1:0] btn;
  wire [7:0] seg0;
  wire [7:0] seg1;
  wire [7:0] seg2;
  wire [7:0] seg3;
  wire [13:0] count_value;


  /*   Clock Generate (50MHz)   */
  always begin
                    clk = 1'b1;
    #HALF_CYCLE     clk = 1'b0;
    #HALF_CYCLE;
  end


  /*   Calling of the modules   */
  SegDecCount #(4) Simulation (clk, rst, btn, seg0, seg1, seg2, seg3, count_value);


  initial begin
    /*   Icarus Verilog   */
    $dumpfile("out.vcd");
    $dumpvars(0, clk, rst, btn, seg0, seg1, seg2, seg3, count_value);

    rst = 1'b1;   btn[0] = 1'b1;   btn[1] = 1'b1;
    #DELAY;         // Racing measures
    #100            rst = 1'b0;   // Reset ON
    #100            rst = 1'b1;   // Reset OFF

    #100  btn[0] = 1'b0;     #100  btn[0] = 1'b1;     // 1st Digit = 1
    #50  btn[1] = 1'b0;     #50  btn[1] = 1'b1;

    #100  btn[0] = 1'b0;     #100  btn[0] = 1'b1;     // 2nd Digit = 0


    #100  btn[0] = 1'b0;     #100  btn[0] = 1'b1;     // 3rd Digit = 5
    #50  btn[1] = 1'b0;     #50  btn[1] = 1'b1;
    #50  btn[1] = 1'b0;     #50  btn[1] = 1'b1;
    #50  btn[1] = 1'b0;     #50  btn[1] = 1'b1;
    #50  btn[1] = 1'b0;     #50  btn[1] = 1'b1;
    #50  btn[1] = 1'b0;     #50  btn[1] = 1'b1;

    #100  btn[0] = 1'b0;     #100  btn[0] = 1'b1;     // 4th Digit = 2
    #50  btn[1] = 1'b0;     #50  btn[1] = 1'b1;
    #50  btn[1] = 1'b0;     #50  btn[1] = 1'b1;

    #100  btn[0] = 1'b0;     #100  btn[0] = 1'b1;     // Output Adder

    #(10*CYCLE)    $finish;
  end


endmodule

SegDecCount/out.vcd
$date
	Sun Apr 13 13:01:36 2014
$end
$version
	Icarus Verilog
$end
$timescale
	1ns
$end
$scope module Simulator $end
$var reg 1 ! clk $end
$upscope $end
$scope module Simulator $end
$var reg 1 " rst $end
$upscope $end
$scope module Simulator $end
$var reg 2 # btn [1:0] $end
$upscope $end
$scope module Simulator $end
$var wire 8 $ seg0 [7:0] $end
$upscope $end
$scope module Simulator $end
$var wire 8 % seg1 [7:0] $end
$upscope $end
$scope module Simulator $end
$var wire 8 & seg2 [7:0] $end
$upscope $end
$scope module Simulator $end
$var wire 8 ' seg3 [7:0] $end
$upscope $end
$scope module Simulator $end
$var wire 14 ( count_value [13:0] $end
$upscope $end
$enddefinitions $end
#0
$dumpvars
b0 (
b11000000 '
b11000000 &
b11000000 %
b11000000 $
b11 #
1"
1!
$end
#10
0!
#20
1!
#30
0!
#40
1!
#50
0!
#60
1!
#70
0!
#80
1!
#90
0!
#100
1!
#110
b0 $
b0 %
b0 &
b0 '
0!
0"
#120
1!
#130
0!
#140
1!
#150
0!
#160
1!
#170
0!
#180
1!
#190
0!
#200
1!
#210
b11000000 $
b11000000 %
b11000000 &
b11000000 '
0!
1"
#220
1!
#230
0!
#240
1!
#250
0!
#260
1!
#270
0!
#280
1!
#290
0!
#300
1!
#310
0!
b10 #
#320
1!
#330
0!
#340
1!
#350
0!
#360
1!
#370
0!
#380
1!
#390
0!
#400
1!
#410
0!
b11 #
#420
1!
#430
0!
#440
1!
#450
0!
#460
b11111001 $
b11111001 %
b11111001 &
b11111001 '
b10001010111 (
1!
b1 #
#470
0!
#480
1!
#490
0!
#500
1!
#510
0!
b11 #
#520
1!
#530
0!
#540
1!
#550
0!
#560
1!
#570
0!
#580
1!
#590
0!
#600
1!
#610
0!
b10 #
#620
1!
#630
0!
#640
1!
#650
0!
#660
1!
#670
0!
#680
1!
#690
0!
#700
1!
#710
0!
b11 #
#720
1!
#730
0!
#740
1!
#750
0!
#760
1!
#770
0!
#780
1!
#790
0!
#800
1!
#810
0!
b10 #
#820
1!
#830
0!
#840
1!
#850
0!
#860
1!
#870
0!
#880
1!
#890
0!
#900
1!
#910
0!
b11 #
#920
1!
#930
0!
#940
1!
#950
0!
#960
b10100100 &
b10100100 $
b10100100 %
b10100100 '
b100010101110 (
1!
b1 #
#970
0!
#980
1!
#990
0!
#1000
1!
#1010
0!
b11 #
#1020
1!
#1030
0!
#1040
1!
#1050
0!
#1060
b10110000 &
b10110000 $
b10110000 %
b10110000 '
b110100000101 (
1!
b1 #
#1070
0!
#1080
1!
#1090
0!
#1100
1!
#1110
0!
b11 #
#1120
1!
#1130
0!
#1140
1!
#1150
0!
#1160
b10011001 &
b10011001 $
b10011001 %
b10011001 '
b1000101011100 (
1!
b1 #
#1170
0!
#1180
1!
#1190
0!
#1200
1!
#1210
0!
b11 #
#1220
1!
#1230
0!
#1240
1!
#1250
0!
#1260
b10010010 &
b10010010 $
b10010010 %
b10010010 '
b1010110110011 (
1!
b1 #
#1270
0!
#1280
1!
#1290
0!
#1300
1!
#1310
0!
b11 #
#1320
1!
#1330
0!
#1340
1!
#1350
0!
#1360
b10000010 &
b10000010 $
b10000010 %
b10000010 '
b1101000001010 (
1!
b1 #
#1370
0!
#1380
1!
#1390
0!
#1400
1!
#1410
0!
b11 #
#1420
1!
#1430
0!
#1440
1!
#1450
0!
#1460
1!
#1470
0!
#1480
1!
#1490
0!
#1500
1!
#1510
0!
b10 #
#1520
1!
#1530
0!
#1540
1!
#1550
0!
#1560
1!
#1570
0!
#1580
1!
#1590
0!
#1600
1!
#1610
0!
b11 #
#1620
1!
#1630
0!
#1640
1!
#1650
0!
#1660
b11111000 '
b11111000 $
b11111000 %
b11111000 &
b1111001100001 (
1!
b1 #
#1670
0!
#1680
1!
#1690
0!
#1700
1!
#1710
0!
b11 #
#1720
1!
#1730
0!
#1740
1!
#1750
0!
#1760
b10000000 '
b10000000 $
b10000000 %
b10000000 &
b10001010111000 (
1!
b1 #
#1770
0!
#1780
1!
#1790
0!
#1800
1!
#1810
0!
b11 #
#1820
1!
#1830
0!
#1840
1!
#1850
0!
#1860
1!
#1870
0!
#1880
1!
#1890
0!
#1900
1!
#1910
0!
b10 #
#1920
1!
#1930
0!
#1940
1!
#1950
0!
#1960
1!
#1970
0!
#1980
1!
#1990
0!
#2000
1!
#2010
0!
b11 #
